fengluU/__init__.py
fengluU/mysql_alter.py
fengluU/mysql_helper.py
fengluU/n2u.py
fengluU/rmb2u.py
fengluU/sendmsg.py
fenglub-0.0.4a1.dist-info/licenses/LICENSE
fenglub-0.0.4a1.dist-info/METADATA
fenglub-0.0.4a1.dist-info/WHEEL
fenglub-0.0.4a1.dist-info/top_level.txt
fenglub-0.0.4a1.dist-info/RECORD
