Metadata-Version: 2.4
Name: fengluB
Version: 0.0.4a1
Summary: 牛逢路的开发工具包
Home-page: https://github.com/ccooder/fengluU
Author: Fenglu Niu
Author-email: niufenglu@gmail.com
Classifier: Programming Language :: Python :: 3.9
Classifier: License :: OSI Approved :: MIT License
Classifier: Operating System :: OS Independent
Requires-Python: >=3.6
License-File: LICENSE
Requires-Dist: mysql-connector-python
Requires-Dist: regex
Dynamic: author
Dynamic: author-email
Dynamic: classifier
Dynamic: description
Dynamic: description-content-type
Dynamic: home-page
Dynamic: license-file
Dynamic: requires-dist
Dynamic: requires-python
Dynamic: summary
